.gitignore
README.rst
bootstrap.py
buildout.cfg
setup.cfg
setup.py
docs/HISTORY.txt
docs/INSTALL.txt
docs/LICENSE.GPL
docs/LICENSE.txt
transmogrify/__init__.py
transmogrify.siteanalyser.egg-info/PKG-INFO
transmogrify.siteanalyser.egg-info/SOURCES.txt
transmogrify.siteanalyser.egg-info/dependency_links.txt
transmogrify.siteanalyser.egg-info/entry_points.txt
transmogrify.siteanalyser.egg-info/namespace_packages.txt
transmogrify.siteanalyser.egg-info/not-zip-safe
transmogrify.siteanalyser.egg-info/requires.txt
transmogrify.siteanalyser.egg-info/top_level.txt
transmogrify/siteanalyser/__init__.py
transmogrify/siteanalyser/backlinkstitle.py
transmogrify/siteanalyser/configure.zcml
transmogrify/siteanalyser/guesshidefromnav.py
transmogrify/siteanalyser/isindex.py
transmogrify/siteanalyser/isindex.txt
transmogrify/siteanalyser/makeattachments.py
transmogrify/siteanalyser/makeattachments.txt
transmogrify/siteanalyser/relinker.py
transmogrify/siteanalyser/relinker.txt
transmogrify/siteanalyser/sitemapper.py
transmogrify/siteanalyser/tests.py
transmogrify/siteanalyser/treeserializer.py
transmogrify/siteanalyser/treeserializer.txt
transmogrify/siteanalyser/urltidy.py
transmogrify/siteanalyser/external/__init__.py
transmogrify/siteanalyser/external/base.py
transmogrify/siteanalyser/external/normalize.py
transmogrify/siteanalyser/external/relative_url.py