Metadata-Version: 1.0
Name: transmogrify.siteanalyser
Version: 1.3
Summary: transmogrifier source blueprints for crawling html
Home-page: http://github.com/collective/transmogrify.siteanalyser
Author: Dylan Jay
Author-email: software@pretaweb.com
License: GPL
Keywords: transmogrifier blueprint funnelweb source plone import conversion microsoft office
Platform: UNKNOWN
Classifier: Programming Language :: Python
Classifier: Topic :: Software Development :: Libraries :: Python Modules
